xiyan_leeb_server/__main__.py
xiyan_leeb_server/config_demo.yml
xiyan_leeb_server/database_env.py
xiyan_leeb_server/server.py
xiyan_leeb_server/local_model/README.md
xiyan_leeb_server/local_model/local_xiyan_server.py
xiyan_leeb_server/utils/common_util.py
xiyan_leeb_server/utils/db_config.py
xiyan_leeb_server/utils/db_mschema.py
xiyan_leeb_server/utils/db_source.py
xiyan_leeb_server/utils/db_util.py
xiyan_leeb_server/utils/file_util.py
xiyan_leeb_server/utils/llm_util.py
xiyan_leeb_server/utils/logger_util.py
xiyan_leeb_server-0.1.6.dev0.dist-info/METADATA
xiyan_leeb_server-0.1.6.dev0.dist-info/WHEEL
xiyan_leeb_server-0.1.6.dev0.dist-info/entry_points.txt
xiyan_leeb_server-0.1.6.dev0.dist-info/licenses/LICENSE.txt
xiyan_leeb_server-0.1.6.dev0.dist-info/RECORD
